{
    "2022-01-06-01/1to82": [
        [
            102,
            31,
            32
        ],
        [
            105,
            35,
            33
        ]
    ],
    "2022-01-06-01/1to97": [
        [
            102,
            31,
            32
        ],
        [
            113,
            43,
            32
        ]
    ],
    "2022-01-06-01/1to122": [
        [
            102,
            31,
            32
        ],
        [
            108,
            75,
            34
        ]
    ],
    "2022-01-06-01/1to162": [
        [
            102,
            31,
            32
        ],
        [
            123,
            80,
            28
        ]
    ],
    "2022-01-06-01/1to246": [
        [
            102,
            31,
            32
        ],
        [
            109,
            49,
            33
        ]
    ],
    "2022-01-06-01/1to272": [
        [
            102,
            31,
            32
        ],
        [
            99,
            65,
            32
        ]
    ],
    "2022-01-06-01/1to294": [
        [
            102,
            31,
            32
        ],
        [
            104,
            31,
            32
        ]
    ],
    "2022-01-06-01/1to372": [
        [
            102,
            31,
            32
        ],
        [
            78,
            41,
            32
        ]
    ],
    "2022-01-06-01/1to650": [
        [
            102,
            31,
            32
        ],
        [
            111,
            61,
            33
        ]
    ],
    "2022-01-06-01/1to651": [
        [
            102,
            31,
            32
        ],
        [
            111,
            48,
            33
        ]
    ],
    "2022-01-06-01/1to671": [
        [
            102,
            31,
            32
        ],
        [
            106,
            35,
            34
        ]
    ],
    "2022-01-06-01/1to691": [
        [
            102,
            31,
            32
        ],
        [
            146,
            40,
            38
        ]
    ],
    "2022-01-06-01/1to722": [
        [
            102,
            31,
            32
        ],
        [
            114,
            53,
            34
        ]
    ],
    "2022-01-06-01/2to212": [
        [
            109,
            43,
            30
        ],
        [
            108,
            32,
            33
        ]
    ],
    "2022-01-06-01/2to224": [
        [
            109,
            43,
            30
        ],
        [
            105,
            45,
            33
        ]
    ],
    "2022-01-06-01/2to372": [
        [
            109,
            43,
            30
        ],
        [
            78,
            41,
            32
        ]
    ],
    "2022-01-06-01/2to454": [
        [
            109,
            43,
            30
        ],
        [
            107,
            53,
            30
        ]
    ],
    "2022-01-06-01/2to478": [
        [
            109,
            43,
            30
        ],
        [
            102,
            52,
            31
        ]
    ],
    "2022-01-06-01/2to528": [
        [
            109,
            43,
            30
        ],
        [
            103,
            52,
            31
        ]
    ],
    "2022-01-06-01/2to571": [
        [
            109,
            43,
            30
        ],
        [
            153,
            44,
            32
        ]
    ],
    "2022-01-06-01/2to609": [
        [
            109,
            43,
            30
        ],
        [
            100,
            50,
            33
        ]
    ],
    "2022-01-06-01/2to610": [
        [
            109,
            43,
            30
        ],
        [
            105,
            49,
            33
        ]
    ],
    "2022-01-06-01/2to611": [
        [
            109,
            43,
            30
        ],
        [
            110,
            36,
            33
        ]
    ],
    "2022-01-06-01/2to671": [
        [
            109,
            43,
            30
        ],
        [
            106,
            35,
            34
        ]
    ],
    "2022-01-06-01/2to691": [
        [
            109,
            43,
            30
        ],
        [
            146,
            40,
            38
        ]
    ],
    "2022-01-06-01/3to47": [
        [
            93,
            45,
            33
        ],
        [
            110,
            75,
            33
        ]
    ],
    "2022-01-06-01/3to70": [
        [
            93,
            45,
            33
        ],
        [
            121,
            39,
            33
        ]
    ],
    "2022-01-06-01/3to137": [
        [
            93,
            45,
            33
        ],
        [
            69,
            46,
            33
        ]
    ],
    "2022-01-06-01/3to588": [
        [
            93,
            45,
            33
        ],
        [
            130,
            47,
            33
        ]
    ],
    "2022-01-06-01/3to589": [
        [
            93,
            45,
            33
        ],
        [
            130,
            47,
            34
        ]
    ],
    "2022-01-06-01/3to590": [
        [
            93,
            45,
            33
        ],
        [
            121,
            44,
            34
        ]
    ],
    "2022-01-06-01/3to591": [
        [
            93,
            45,
            33
        ],
        [
            119,
            46,
            34
        ]
    ],
    "2022-01-06-01/3to658": [
        [
            93,
            45,
            33
        ],
        [
            116,
            53,
            32
        ]
    ],
    "2022-01-06-01/3to687": [
        [
            93,
            45,
            33
        ],
        [
            147,
            40,
            34
        ]
    ],
    "2022-01-06-01/3to688": [
        [
            93,
            45,
            33
        ],
        [
            144,
            39,
            34
        ]
    ],
    "2022-01-06-01/3to689": [
        [
            93,
            45,
            33
        ],
        [
            123,
            39,
            33
        ]
    ],
    "2022-01-06-01/3to703": [
        [
            93,
            45,
            33
        ],
        [
            109,
            57,
            32
        ]
    ],
    "2022-01-06-01/4to55": [
        [
            165,
            49,
            33
        ],
        [
            138,
            54,
            35
        ]
    ],
    "2022-01-06-01/4to117": [
        [
            165,
            49,
            33
        ],
        [
            97,
            86,
            35
        ]
    ],
    "2022-01-06-01/4to140": [
        [
            165,
            49,
            33
        ],
        [
            203,
            78,
            35
        ]
    ],
    "2022-01-06-01/4to184": [
        [
            165,
            49,
            33
        ],
        [
            129,
            39,
            31
        ]
    ],
    "2022-01-06-01/4to226": [
        [
            165,
            49,
            33
        ],
        [
            114,
            57,
            33
        ]
    ],
    "2022-01-06-01/4to234": [
        [
            165,
            49,
            33
        ],
        [
            56,
            46,
            34
        ]
    ],
    "2022-01-06-01/4to429": [
        [
            165,
            49,
            33
        ],
        [
            97,
            47,
            31
        ]
    ],
    "2022-01-06-01/4to562": [
        [
            165,
            49,
            33
        ],
        [
            100,
            49,
            32
        ]
    ],
    "2022-01-06-01/4to634": [
        [
            165,
            49,
            33
        ],
        [
            161,
            34,
            34
        ]
    ],
    "2022-01-06-01/4to675": [
        [
            165,
            49,
            33
        ],
        [
            80,
            66,
            34
        ]
    ],
    "2022-01-06-01/5to33": [
        [
            116,
            154,
            33
        ],
        [
            105,
            62,
            31
        ]
    ],
    "2022-01-06-01/5to91": [
        [
            116,
            154,
            33
        ],
        [
            111,
            60,
            37
        ]
    ],
    "2022-01-06-01/5to104": [
        [
            116,
            154,
            33
        ],
        [
            92,
            58,
            36
        ]
    ],
    "2022-01-06-01/5to191": [
        [
            116,
            154,
            33
        ],
        [
            83,
            58,
            31
        ]
    ],
    "2022-01-06-01/5to371": [
        [
            116,
            154,
            33
        ],
        [
            96,
            44,
            31
        ]
    ],
    "2022-01-06-01/5to394": [
        [
            116,
            154,
            33
        ],
        [
            106,
            44,
            32
        ]
    ],
    "2022-01-06-01/5to410": [
        [
            116,
            154,
            33
        ],
        [
            101,
            47,
            32
        ]
    ],
    "2022-01-06-01/5to412": [
        [
            116,
            154,
            33
        ],
        [
            83,
            43,
            31
        ]
    ],
    "2022-01-06-01/5to500": [
        [
            116,
            154,
            33
        ],
        [
            110,
            49,
            33
        ]
    ],
    "2022-01-06-01/5to720": [
        [
            116,
            154,
            33
        ],
        [
            84,
            44,
            32
        ]
    ],
    "2022-01-06-01/6to142": [
        [
            91,
            45,
            34
        ],
        [
            115,
            35,
            34
        ]
    ],
    "2022-01-06-01/6to205": [
        [
            91,
            45,
            34
        ],
        [
            94,
            99,
            32
        ]
    ],
    "2022-01-06-01/6to301": [
        [
            91,
            45,
            34
        ],
        [
            108,
            48,
            33
        ]
    ],
    "2022-01-06-01/6to401": [
        [
            91,
            45,
            34
        ],
        [
            83,
            44,
            33
        ]
    ],
    "2022-01-06-01/6to466": [
        [
            91,
            45,
            34
        ],
        [
            141,
            44,
            32
        ]
    ],
    "2022-01-06-01/6to523": [
        [
            91,
            45,
            34
        ],
        [
            143,
            34,
            32
        ]
    ],
    "2022-01-06-01/6to566": [
        [
            91,
            45,
            34
        ],
        [
            115,
            47,
            32
        ]
    ],
    "2022-01-06-01/6to596": [
        [
            91,
            45,
            34
        ],
        [
            107,
            43,
            35
        ]
    ],
    "2022-01-06-01/6to636": [
        [
            91,
            45,
            34
        ],
        [
            101,
            37,
            34
        ]
    ],
    "2022-01-06-01/6to749": [
        [
            91,
            45,
            34
        ],
        [
            103,
            44,
            34
        ]
    ],
    "2022-01-06-01/6to754": [
        [
            91,
            45,
            34
        ],
        [
            99,
            42,
            33
        ]
    ],
    "2022-01-06-01/6to763": [
        [
            91,
            45,
            34
        ],
        [
            97,
            43,
            34
        ]
    ],
    "2022-01-06-01/6to764": [
        [
            91,
            45,
            34
        ],
        [
            100,
            41,
            33
        ]
    ],
    "2022-01-06-01/6to766": [
        [
            91,
            45,
            34
        ],
        [
            102,
            42,
            34
        ]
    ],
    "2022-01-06-01/6to778": [
        [
            91,
            45,
            34
        ],
        [
            107,
            39,
            33
        ]
    ],
    "2022-01-06-01/6to791": [
        [
            91,
            45,
            34
        ],
        [
            100,
            43,
            34
        ]
    ],
    "2022-01-06-01/6to793": [
        [
            91,
            45,
            34
        ],
        [
            100,
            43,
            34
        ]
    ],
    "2022-01-06-01/6to794": [
        [
            91,
            45,
            34
        ],
        [
            100,
            42,
            33
        ]
    ],
    "2022-01-06-01/6to795": [
        [
            91,
            45,
            34
        ],
        [
            98,
            42,
            34
        ]
    ],
    "2022-01-06-01/6to797": [
        [
            91,
            45,
            34
        ],
        [
            87,
            40,
            33
        ]
    ],
    "2022-01-06-01/6to798": [
        [
            91,
            45,
            34
        ],
        [
            87,
            43,
            34
        ]
    ],
    "2022-01-06-01/7to12": [
        [
            80,
            61,
            34
        ],
        [
            122,
            65,
            37
        ]
    ],
    "2022-01-06-01/7to229": [
        [
            80,
            61,
            34
        ],
        [
            86,
            71,
            35
        ]
    ],
    "2022-01-06-01/7to361": [
        [
            80,
            61,
            34
        ],
        [
            137,
            163,
            34
        ]
    ],
    "2022-01-06-01/7to366": [
        [
            80,
            61,
            34
        ],
        [
            89,
            37,
            34
        ]
    ],
    "2022-01-06-01/7to403": [
        [
            80,
            61,
            34
        ],
        [
            78,
            39,
            33
        ]
    ],
    "2022-01-06-01/7to422": [
        [
            80,
            61,
            34
        ],
        [
            130,
            67,
            34
        ]
    ],
    "2022-01-06-01/7to440": [
        [
            80,
            61,
            34
        ],
        [
            88,
            42,
            32
        ]
    ],
    "2022-01-06-01/7to441": [
        [
            80,
            61,
            34
        ],
        [
            80,
            35,
            32
        ]
    ],
    "2022-01-06-01/7to442": [
        [
            80,
            61,
            34
        ],
        [
            82,
            38,
            32
        ]
    ],
    "2022-01-06-01/7to539": [
        [
            80,
            61,
            34
        ],
        [
            81,
            36,
            33
        ]
    ],
    "2022-01-06-01/7to796": [
        [
            80,
            61,
            34
        ],
        [
            87,
            42,
            33
        ]
    ],
    "2022-01-06-01/8to29": [
        [
            136,
            60,
            35
        ],
        [
            79,
            68,
            32
        ]
    ],
    "2022-01-06-01/8to64": [
        [
            136,
            60,
            35
        ],
        [
            136,
            61,
            35
        ]
    ],
    "2022-01-06-01/8to101": [
        [
            136,
            60,
            35
        ],
        [
            91,
            38,
            36
        ]
    ],
    "2022-01-06-01/8to102": [
        [
            136,
            60,
            35
        ],
        [
            81,
            39,
            36
        ]
    ],
    "2022-01-06-01/8to125": [
        [
            136,
            60,
            35
        ],
        [
            89,
            54,
            34
        ]
    ],
    "2022-01-06-01/8to147": [
        [
            136,
            60,
            35
        ],
        [
            95,
            33,
            36
        ]
    ],
    "2022-01-06-01/8to176": [
        [
            136,
            60,
            35
        ],
        [
            92,
            40,
            32
        ]
    ],
    "2022-01-06-01/8to177": [
        [
            136,
            60,
            35
        ],
        [
            84,
            40,
            32
        ]
    ],
    "2022-01-06-01/8to298": [
        [
            136,
            60,
            35
        ],
        [
            134,
            55,
            33
        ]
    ],
    "2022-01-06-01/8to299": [
        [
            136,
            60,
            35
        ],
        [
            133,
            57,
            34
        ]
    ],
    "2022-01-06-01/8to317": [
        [
            136,
            60,
            35
        ],
        [
            82,
            42,
            36
        ]
    ],
    "2022-01-06-02/1to2": [
        [
            110,
            45,
            33
        ],
        [
            116,
            45,
            32
        ]
    ],
    "2022-01-06-02/1to3": [
        [
            110,
            45,
            33
        ],
        [
            102,
            53,
            32
        ]
    ],
    "2022-01-06-02/1to6": [
        [
            110,
            45,
            33
        ],
        [
            108,
            48,
            34
        ]
    ],
    "2022-01-06-02/1to14": [
        [
            110,
            45,
            33
        ],
        [
            105,
            116,
            34
        ]
    ],
    "2022-01-06-02/1to16": [
        [
            110,
            45,
            33
        ],
        [
            120,
            135,
            35
        ]
    ],
    "2022-01-06-02/1to53": [
        [
            110,
            45,
            33
        ],
        [
            103,
            48,
            35
        ]
    ],
    "2022-01-06-02/1to80": [
        [
            110,
            45,
            33
        ],
        [
            121,
            89,
            37
        ]
    ],
    "2022-01-06-02/1to306": [
        [
            110,
            45,
            33
        ],
        [
            119,
            40,
            33
        ]
    ],
    "2022-01-06-02/1to487": [
        [
            110,
            45,
            33
        ],
        [
            116,
            42,
            32
        ]
    ],
    "2022-01-06-02/1to489": [
        [
            110,
            45,
            33
        ],
        [
            127,
            41,
            32
        ]
    ],
    "2022-01-06-02/1to490": [
        [
            110,
            45,
            33
        ],
        [
            128,
            40,
            32
        ]
    ],
    "2022-01-06-02/1to553": [
        [
            110,
            45,
            33
        ],
        [
            124,
            45,
            31
        ]
    ],
    "2022-01-06-02/1to557": [
        [
            110,
            45,
            33
        ],
        [
            125,
            39,
            31
        ]
    ],
    "2022-01-06-02/2to4": [
        [
            116,
            45,
            32
        ],
        [
            110,
            46,
            32
        ]
    ],
    "2022-01-06-02/2to16": [
        [
            116,
            45,
            32
        ],
        [
            120,
            135,
            35
        ]
    ],
    "2022-01-06-02/2to27": [
        [
            116,
            45,
            32
        ],
        [
            187,
            38,
            35
        ]
    ],
    "2022-01-06-02/2to31": [
        [
            116,
            45,
            32
        ],
        [
            107,
            45,
            34
        ]
    ],
    "2022-01-06-02/2to224": [
        [
            116,
            45,
            32
        ],
        [
            105,
            75,
            34
        ]
    ],
    "2022-01-06-02/2to487": [
        [
            116,
            45,
            32
        ],
        [
            116,
            42,
            32
        ]
    ],
    "2022-01-06-02/2to489": [
        [
            116,
            45,
            32
        ],
        [
            127,
            41,
            32
        ]
    ],
    "2022-01-06-02/2to490": [
        [
            116,
            45,
            32
        ],
        [
            128,
            40,
            32
        ]
    ],
    "2022-01-06-02/2to491": [
        [
            116,
            45,
            32
        ],
        [
            127,
            40,
            31
        ]
    ],
    "2022-01-06-02/2to557": [
        [
            116,
            45,
            32
        ],
        [
            125,
            39,
            31
        ]
    ],
    "2022-01-06-02/2to563": [
        [
            116,
            45,
            32
        ],
        [
            123,
            39,
            31
        ]
    ],
    "2022-01-06-02/3to5": [
        [
            102,
            53,
            32
        ],
        [
            111,
            47,
            33
        ]
    ],
    "2022-01-06-02/3to6": [
        [
            102,
            53,
            32
        ],
        [
            108,
            48,
            34
        ]
    ],
    "2022-01-06-02/3to14": [
        [
            102,
            53,
            32
        ],
        [
            105,
            116,
            34
        ]
    ],
    "2022-01-06-02/3to16": [
        [
            102,
            53,
            32
        ],
        [
            120,
            135,
            35
        ]
    ],
    "2022-01-06-02/3to41": [
        [
            102,
            53,
            32
        ],
        [
            98,
            53,
            34
        ]
    ],
    "2022-01-06-02/3to49": [
        [
            102,
            53,
            32
        ],
        [
            102,
            48,
            35
        ]
    ],
    "2022-01-06-02/3to52": [
        [
            102,
            53,
            32
        ],
        [
            106,
            49,
            36
        ]
    ],
    "2022-01-06-02/3to54": [
        [
            102,
            53,
            32
        ],
        [
            103,
            49,
            35
        ]
    ],
    "2022-01-06-02/3to63": [
        [
            102,
            53,
            32
        ],
        [
            101,
            52,
            36
        ]
    ],
    "2022-01-06-02/3to77": [
        [
            102,
            53,
            32
        ],
        [
            119,
            72,
            37
        ]
    ],
    "2022-01-06-02/3to78": [
        [
            102,
            53,
            32
        ],
        [
            118,
            87,
            37
        ]
    ],
    "2022-01-06-02/3to787": [
        [
            102,
            53,
            32
        ],
        [
            70,
            46,
            31
        ]
    ],
    "2022-01-06-02/4to8": [
        [
            110,
            46,
            32
        ],
        [
            94,
            46,
            32
        ]
    ],
    "2022-01-06-02/4to201": [
        [
            110,
            46,
            32
        ],
        [
            123,
            39,
            36
        ]
    ],
    "2022-01-06-02/4to223": [
        [
            110,
            46,
            32
        ],
        [
            101,
            65,
            35
        ]
    ],
    "2022-01-06-02/4to294": [
        [
            110,
            46,
            32
        ],
        [
            118,
            52,
            34
        ]
    ],
    "2022-01-06-02/4to303": [
        [
            110,
            46,
            32
        ],
        [
            116,
            40,
            32
        ]
    ],
    "2022-01-06-02/4to427": [
        [
            110,
            46,
            32
        ],
        [
            85,
            36,
            32
        ]
    ],
    "2022-01-06-02/4to552": [
        [
            110,
            46,
            32
        ],
        [
            109,
            48,
            32
        ]
    ],
    "2022-01-06-02/4to557": [
        [
            110,
            46,
            32
        ],
        [
            125,
            39,
            31
        ]
    ],
    "2022-01-06-02/4to680": [
        [
            110,
            46,
            32
        ],
        [
            126,
            39,
            32
        ]
    ],
    "2022-01-06-02/5to6": [
        [
            111,
            47,
            33
        ],
        [
            108,
            48,
            34
        ]
    ],
    "2022-01-06-02/5to16": [
        [
            111,
            47,
            33
        ],
        [
            120,
            135,
            35
        ]
    ],
    "2022-01-06-02/5to45": [
        [
            111,
            47,
            33
        ],
        [
            103,
            47,
            35
        ]
    ],
    "2022-01-06-02/5to49": [
        [
            111,
            47,
            33
        ],
        [
            102,
            48,
            35
        ]
    ],
    "2022-01-06-02/5to51": [
        [
            111,
            47,
            33
        ],
        [
            103,
            48,
            35
        ]
    ],
    "2022-01-06-02/5to52": [
        [
            111,
            47,
            33
        ],
        [
            106,
            49,
            36
        ]
    ],
    "2022-01-06-02/5to54": [
        [
            111,
            47,
            33
        ],
        [
            103,
            49,
            35
        ]
    ],
    "2022-01-06-02/5to55": [
        [
            111,
            47,
            33
        ],
        [
            101,
            49,
            35
        ]
    ],
    "2022-01-06-02/5to58": [
        [
            111,
            47,
            33
        ],
        [
            97,
            48,
            36
        ]
    ],
    "2022-01-06-02/5to60": [
        [
            111,
            47,
            33
        ],
        [
            102,
            49,
            36
        ]
    ],
    "2022-01-06-02/5to61": [
        [
            111,
            47,
            33
        ],
        [
            99,
            49,
            36
        ]
    ],
    "2022-01-06-02/5to63": [
        [
            111,
            47,
            33
        ],
        [
            101,
            52,
            36
        ]
    ],
    "2022-01-06-02/5to303": [
        [
            111,
            47,
            33
        ],
        [
            116,
            40,
            32
        ]
    ],
    "2022-01-06-02/5to351": [
        [
            111,
            47,
            33
        ],
        [
            151,
            49,
            32
        ]
    ],
    "2022-01-06-02/5to361": [
        [
            111,
            47,
            33
        ],
        [
            153,
            41,
            32
        ]
    ],
    "2022-01-06-02/5to787": [
        [
            111,
            47,
            33
        ],
        [
            70,
            46,
            31
        ]
    ],
    "2022-01-06-02/6to14": [
        [
            108,
            48,
            34
        ],
        [
            105,
            116,
            34
        ]
    ],
    "2022-01-06-02/6to16": [
        [
            108,
            48,
            34
        ],
        [
            120,
            135,
            35
        ]
    ],
    "2022-01-06-02/6to41": [
        [
            108,
            48,
            34
        ],
        [
            98,
            53,
            34
        ]
    ],
    "2022-01-06-02/6to43": [
        [
            108,
            48,
            34
        ],
        [
            105,
            47,
            35
        ]
    ],
    "2022-01-06-02/6to44": [
        [
            108,
            48,
            34
        ],
        [
            102,
            46,
            34
        ]
    ],
    "2022-01-06-02/6to45": [
        [
            108,
            48,
            34
        ],
        [
            103,
            47,
            35
        ]
    ],
    "2022-01-06-02/6to46": [
        [
            108,
            48,
            34
        ],
        [
            105,
            46,
            34
        ]
    ],
    "2022-01-06-02/6to49": [
        [
            108,
            48,
            34
        ],
        [
            102,
            48,
            35
        ]
    ],
    "2022-01-06-02/6to50": [
        [
            108,
            48,
            34
        ],
        [
            105,
            49,
            35
        ]
    ],
    "2022-01-06-02/6to51": [
        [
            108,
            48,
            34
        ],
        [
            103,
            48,
            35
        ]
    ],
    "2022-01-06-02/6to52": [
        [
            108,
            48,
            34
        ],
        [
            106,
            49,
            36
        ]
    ],
    "2022-01-06-02/6to351": [
        [
            108,
            48,
            34
        ],
        [
            151,
            49,
            32
        ]
    ],
    "2022-01-06-02/6to787": [
        [
            108,
            48,
            34
        ],
        [
            70,
            46,
            31
        ]
    ],
    "2022-01-06-02/7to10": [
        [
            110,
            48,
            33
        ],
        [
            114,
            51,
            33
        ]
    ],
    "2022-01-06-02/7to11": [
        [
            110,
            48,
            33
        ],
        [
            107,
            49,
            34
        ]
    ],
    "2022-01-06-02/7to72": [
        [
            110,
            48,
            33
        ],
        [
            120,
            53,
            36
        ]
    ],
    "2022-01-06-02/7to74": [
        [
            110,
            48,
            33
        ],
        [
            119,
            52,
            36
        ]
    ],
    "2022-01-06-02/7to75": [
        [
            110,
            48,
            33
        ],
        [
            122,
            51,
            36
        ]
    ],
    "2022-01-06-02/7to79": [
        [
            110,
            48,
            33
        ],
        [
            120,
            53,
            37
        ]
    ],
    "2022-01-06-02/7to95": [
        [
            110,
            48,
            33
        ],
        [
            101,
            53,
            37
        ]
    ],
    "2022-01-06-02/7to107": [
        [
            110,
            48,
            33
        ],
        [
            98,
            44,
            37
        ]
    ],
    "2022-01-06-02/7to111": [
        [
            110,
            48,
            33
        ],
        [
            112,
            51,
            36
        ]
    ],
    "2022-01-06-02/7to368": [
        [
            110,
            48,
            33
        ],
        [
            157,
            36,
            31
        ]
    ],
    "2022-01-06-02/7to414": [
        [
            110,
            48,
            33
        ],
        [
            96,
            48,
            32
        ]
    ],
    "2022-01-06-02/8to163": [
        [
            94,
            46,
            32
        ],
        [
            89,
            43,
            38
        ]
    ],
    "2022-01-06-02/8to165": [
        [
            94,
            46,
            32
        ],
        [
            89,
            42,
            37
        ]
    ],
    "2022-01-06-02/8to169": [
        [
            94,
            46,
            32
        ],
        [
            89,
            43,
            38
        ]
    ],
    "2022-01-06-02/8to171": [
        [
            94,
            46,
            32
        ],
        [
            76,
            48,
            37
        ]
    ],
    "2022-01-06-02/8to176": [
        [
            94,
            46,
            32
        ],
        [
            95,
            41,
            37
        ]
    ],
    "2022-01-06-02/8to197": [
        [
            94,
            46,
            32
        ],
        [
            132,
            67,
            35
        ]
    ],
    "2022-01-06-02/8to290": [
        [
            94,
            46,
            32
        ],
        [
            99,
            112,
            35
        ]
    ],
    "2022-01-06-02/8to295": [
        [
            94,
            46,
            32
        ],
        [
            118,
            51,
            35
        ]
    ],
    "2022-01-06-02/8to301": [
        [
            94,
            46,
            32
        ],
        [
            112,
            40,
            33
        ]
    ],
    "2022-01-06-02/8to398": [
        [
            94,
            46,
            32
        ],
        [
            112,
            50,
            32
        ]
    ],
    "2022-01-06-02/8to427": [
        [
            94,
            46,
            32
        ],
        [
            85,
            36,
            32
        ]
    ],
    "2022-01-06-02/8to436": [
        [
            94,
            46,
            32
        ],
        [
            207,
            68,
            34
        ]
    ],
    "2022-01-06-02/9to10": [
        [
            110,
            49,
            34
        ],
        [
            114,
            51,
            33
        ]
    ],
    "2022-01-06-02/9to11": [
        [
            110,
            49,
            34
        ],
        [
            107,
            49,
            34
        ]
    ],
    "2022-01-06-02/9to12": [
        [
            110,
            49,
            34
        ],
        [
            109,
            50,
            33
        ]
    ]
}